gfiles/__init__.py
gfiles/admin.py
gfiles/apps.py
gfiles/filter.py
gfiles/forms.py
gfiles/models.py
gfiles/sitetrees.py
gfiles/tables.py
gfiles/test_settings.py
gfiles/urls.py
gfiles/views.py
gfiles/migrations/0001_initial.py
gfiles/migrations/__init__.py
gfiles/static/gfiles/show_hide_filters.js
gfiles/static/gfiles/status_updates.js
gfiles/static/gfiles/table_check.js
gfiles/static/gfiles/zip_dir.js
gfiles/templates/base.html
gfiles/templates/template_structure.txt
gfiles/templates/gfiles/404.html
gfiles/templates/gfiles/500.html
gfiles/templates/gfiles/confirm_delete.html
gfiles/templates/gfiles/filter_table.html
gfiles/templates/gfiles/form_errors.html
gfiles/templates/gfiles/form_table.html
gfiles/templates/gfiles/form_table_multiple.html
gfiles/templates/gfiles/formset_table.html
gfiles/templates/gfiles/gfile_form.html
gfiles/templates/gfiles/gfile_summary.html
gfiles/templates/gfiles/index.html
gfiles/templates/gfiles/login.html
gfiles/templates/gfiles/logout.html
gfiles/templates/gfiles/register.html
gfiles/templates/gfiles/simple_form.html
gfiles/templates/gfiles/simple_formset.html
gfiles/templates/gfiles/single_panel.html
gfiles/templates/gfiles/status.html
gfiles/templates/gfiles/success.html
gfiles/templates/gfiles/table_file_select.html
gfiles/templates/gfiles/table_with_filter.html
gfiles/templates/gfiles/table_with_filter_above.html
gfiles/templates/gfiles/table_with_filter_right.html
gfiles/templates/gfiles/table_with_filter_right_include.html
gfiles/templates/gfiles/tracktask_summary.html
gfiles/templates/gfiles/zip_and_dir_file_select.html
gfiles/utils/__init__.py
gfiles/utils/icons.py
gfiles/utils/save_as_symlink.py
tests/__init__.py
tests/test_views.py
django_gfiles-0.0.2.dist-info/LICENSE
django_gfiles-0.0.2.dist-info/METADATA
django_gfiles-0.0.2.dist-info/WHEEL
django_gfiles-0.0.2.dist-info/top_level.txt
django_gfiles-0.0.2.dist-info/RECORD
